PyPharm/__init__.py
PyPharm/constants.py
PyPharm/models/__init__.py
PyPharm/models/compartment_models.py
PyPharm/models/pbpk.py
pypharm-1.6.3.dist-info/METADATA
pypharm-1.6.3.dist-info/WHEEL
pypharm-1.6.3.dist-info/top_level.txt
pypharm-1.6.3.dist-info/RECORD
