Metadata-Version: 2.1
Name: pypharm
Version: 1.6.3
Summary: Module for solving pharmacokinetic problems
Home-page: https://github.com/Krash13/PyPharm
Author: Krash13
Author-email: krasheninnikov.r.s@muctr.ru
License: UNKNOWN
Keywords: pharmacokinetics compartment-model
Platform: UNKNOWN
Classifier: Programming Language :: Python :: 3.9
Classifier: License :: OSI Approved :: BSD License
Classifier: Operating System :: OS Independent
Requires-Python: >=3.9
Requires-Dist: krashemit (>=1.0.0)
Requires-Dist: numpy (>=1.22.1)
Requires-Dist: scipy (<=1.13.0)
Requires-Dist: numba (>=0.58.1)
Requires-Dist: matplotlib (>=3.5.1)
Requires-Dist: graycode (>=1.0.5)
Requires-Dist: numbalsoda (>=0.3.4)
